{
  "__inputs": [
    {
      "name": "DS_PROMETHEUS",
      "label": "Prometheus",
      "description": "",
      "type": "datasource",
      "pluginId": "prometheus",
      "pluginName": "Prometheus"
    },
    {
      "name": "DS_POSTGRESQL",
      "label": "PostgreSQL",
      "description": "",
      "type": "datasource",
      "pluginId": "postgres",
      "pluginName": "PostgreSQL"
    }
  ],
  "__requires": [
    {
      "type": "panel",
      "id": "bargauge",
      "name": "Bar gauge",
      "version": ""
    },
    {
      "type": "panel",
      "id": "gauge",
      "name": "Gauge",
      "version": ""
    },
    {
      "type": "grafana",
      "id": "grafana",
      "name": "Grafana",
      "version": "7.3.7"
    },
    {
      "type": "panel",
      "id": "graph",
      "name": "Graph",
      "version": ""
    },
    {
      "type": "datasource",
      "id": "postgres",
      "name": "PostgreSQL",
      "version": "1.0.0"
    },
    {
      "type": "datasource",
      "id": "prometheus",
      "name": "Prometheus",
      "version": "1.0.0"
    },
    {
      "type": "panel",
      "id": "stat",
      "name": "Stat",
      "version": ""
    },
    {
      "type": "panel",
      "id": "table",
      "name": "Table",
      "version": ""
    }
  ],
  "annotations": {
    "list": [
      {
        "builtIn": 1,
        "datasource": "-- Grafana --",
        "enable": true,
        "hide": true,
        "iconColor": "rgba(0, 211, 255, 1)",
        "name": "Annotations & Alerts",
        "type": "dashboard"
      }
    ]
  },
  "editable": true,
  "gnetId": 14947,
  "graphTooltip": 0,
  "id": null,
  "iteration": 1630319372727,
  "links": [],
  "panels": [
    {
      "collapsed": false,
      "datasource": "${DS_PROMETHEUS}",
      "gridPos": {
        "h": 1,
        "w": 24,
        "x": 0,
        "y": 0
      },
      "id": 2,
      "panels": [],
      "title": "Cloud Configuration",
      "type": "row"
    },
    {
      "datasource": "${DS_PROMETHEUS}",
      "fieldConfig": {
        "defaults": {
          "color": {
            "mode": "thresholds"
          },
          "custom": {},
          "mappings": [
            {
              "from": "2",
              "id": 1,
              "text": "UP",
              "to": "100000000",
              "type": 1,
              "value": "1"
            },
            {
              "from": "",
              "id": 2,
              "text": "No State",
              "to": "",
              "type": 1,
              "value": "0"
            },
            {
              "from": "",
              "id": 3,
              "text": "Blocked (Quota)",
              "to": "",
              "type": 1,
              "value": "2"
            },
            {
              "from": "",
              "id": 4,
              "text": "Paused",
              "to": "",
              "type": 1,
              "value": "3"
            },
            {
              "from": "",
              "id": 5,
              "text": "Shutting Down",
              "to": "",
              "type": 1,
              "value": "4"
            },
            {
              "from": "",
              "id": 6,
              "text": "Shut off",
              "to": "",
              "type": 1,
              "value": "5"
            },
            {
              "from": "",
              "id": 7,
              "text": "Crashed",
              "to": "",
              "type": 1,
              "value": "6"
            },
            {
              "from": "",
              "id": 8,
              "text": "Suspended",
              "to": "",
              "type": 1,
              "value": "7"
            }
          ],
          "thresholds": {
            "mode": "absolute",
            "steps": [
              {
                "color": "green",
                "value": null
              },
              {
                "color": "super-light-green",
                "value": 1
              },
              {
                "color": "#6ED0E0",
                "value": 2
              },
              {
                "color": "light-orange",
                "value": 3
              },
              {
                "color": "super-light-red",
                "value": 4
              },
              {
                "color": "semi-dark-red",
                "value": 5
              },
              {
                "color": "dark-red",
                "value": 6
              },
              {
                "color": "semi-dark-orange",
                "value": 7
              }
            ]
          }
        },
        "overrides": []
      },
      "gridPos": {
        "h": 4,
        "w": 4,
        "x": 0,
        "y": 1
      },
      "id": 6,
      "options": {
        "colorMode": "background",
        "graphMode": "none",
        "justifyMode": "auto",
        "orientation": "auto",
        "reduceOptions": {
          "calcs": [
            "lastNotNull"
          ],
          "fields": "",
          "values": false
        },
        "text": {},
        "textMode": "auto"
      },
      "pluginVersion": "7.3.7",
      "targets": [
        {
          "exemplar": true,
          "expr": "libvirt_domain_info_vstate{domain=\"$domain\"}",
          "interval": "",
          "legendFormat": "",
          "refId": "A"
        }
      ],
      "title": "State",
      "type": "stat"
    },
    {
      "datasource": "${DS_PROMETHEUS}",
      "fieldConfig": {
        "defaults": {
          "color": {
            "mode": "thresholds"
          },
          "custom": {},
          "mappings": [],
          "thresholds": {
            "mode": "absolute",
            "steps": [
              {
                "color": "green",
                "value": null
              },
              {
                "color": "dark-yellow",
                "value": 0
              }
            ]
          }
        },
        "overrides": []
      },
      "gridPos": {
        "h": 3,
        "w": 4,
        "x": 4,
        "y": 1
      },
      "id": 8,
      "options": {
        "colorMode": "value",
        "graphMode": "none",
        "justifyMode": "auto",
        "orientation": "auto",
        "reduceOptions": {
          "calcs": [
            "lastNotNull"
          ],
          "fields": "",
          "values": false
        },
        "text": {},
        "textMode": "auto"
      },
      "pluginVersion": "7.3.7",
      "targets": [
        {
          "exemplar": true,
          "expr": "libvirt_domain_info_virtual_cpus{domain=\"$domain\"}",
          "interval": "",
          "legendFormat": "",
          "refId": "A"
        }
      ],
      "title": "vCPU",
      "type": "stat"
    },
    {
      "datasource": "${DS_PROMETHEUS}",
      "description": "",
      "fieldConfig": {
        "defaults": {
          "color": {
            "mode": "thresholds"
          },
          "custom": {},
          "mappings": [],
          "min": 5,
          "thresholds": {
            "mode": "absolute",
            "steps": [
              {
                "color": "green",
                "value": null
              },
              {
                "color": "#EAB839",
                "value": 80
              },
              {
                "color": "dark-orange",
                "value": 90
              },
              {
                "color": "red",
                "value": 95
              }
            ]
          },
          "unit": "percent"
        },
        "overrides": []
      },
      "gridPos": {
        "h": 4,
        "w": 4,
        "x": 8,
        "y": 1
      },
      "id": 15,
      "options": {
        "reduceOptions": {
          "calcs": [
            "lastNotNull"
          ],
          "fields": "",
          "values": false
        },
        "showThresholdLabels": false,
        "showThresholdMarkers": true,
        "text": {}
      },
      "pluginVersion": "7.3.7",
      "targets": [
        {
          "exemplar": true,
          "expr": "irate(libvirt_domain_info_cpu_time_seconds_total{domain=\"$domain\"}[5m]) * 100 / libvirt_domain_info_virtual_cpus{domain=\"$domain\"}",
          "interval": "",
          "legendFormat": "",
          "refId": "A"
        }
      ],
      "title": "CPU %",
      "type": "gauge"
    },
    {
      "datasource": "${DS_PROMETHEUS}",
      "description": "",
      "fieldConfig": {
        "defaults": {
          "color": {
            "mode": "thresholds"
          },
          "custom": {},
          "mappings": [],
          "thresholds": {
            "mode": "absolute",
            "steps": [
              {
                "color": "green",
                "value": null
              },
              {
                "color": "yellow",
                "value": 80
              },
              {
                "color": "dark-orange",
                "value": 90
              },
              {
                "color": "dark-red",
                "value": 100
              }
            ]
          },
          "unit": "percent"
        },
        "overrides": []
      },
      "gridPos": {
        "h": 4,
        "w": 4,
        "x": 12,
        "y": 1
      },
      "id": 17,
      "options": {
        "reduceOptions": {
          "calcs": [
            "lastNotNull"
          ],
          "fields": "",
          "values": false
        },
        "showThresholdLabels": false,
        "showThresholdMarkers": true,
        "text": {}
      },
      "pluginVersion": "7.3.7",
      "targets": [
        {
          "exemplar": true,
          "expr": "libvirt_domain_memory_stats_used_percent{domain=\"$domain\"}",
          "instant": false,
          "interval": "",
          "legendFormat": "",
          "refId": "A"
        }
      ],
      "title": "MEM %",
      "type": "gauge"
    },
    {
      "datasource": "${DS_POSTGRESQL}",
      "description": "",
      "fieldConfig": {
        "defaults": {
          "color": {
            "mode": "thresholds"
          },
          "custom": {},
          "mappings": [],
          "max": 100,
          "min": 0,
          "thresholds": {
            "mode": "percentage",
            "steps": [
              {
                "color": "light-green",
                "value": null
              },
              {
                "color": "#EAB839",
                "value": 70
              },
              {
                "color": "dark-orange",
                "value": 80
              },
              {
                "color": "dark-red",
                "value": 90
              }
            ]
          },
          "unit": "percent"
        },
        "overrides": []
      },
      "gridPos": {
        "h": 8,
        "w": 7,
        "x": 16,
        "y": 1
      },
      "id": 44,
      "options": {
        "displayMode": "lcd",
        "orientation": "horizontal",
        "reduceOptions": {
          "calcs": [
            "mean"
          ],
          "fields": "",
          "values": false
        },
        "showUnfilled": true
      },
      "pluginVersion": "7.3.7",
      "targets": [
        {
          "format": "time_series",
          "group": [],
          "metricColumn": "none",
          "rawQuery": true,
          "rawSql": "SELECT\n  ceph_volumes.created_at AS \"time\",\n  (ceph_volumes.usedsize/ceph_volumes.totalsize::float)*100,\n  openstack_volumes.device AS metric\nFROM ceph_volumes\nINNER JOIN openstack_volumes\nON ceph_volumes.id = openstack_volumes.id\n  AND openstack_volumes.status = 'in-use'\n  AND openstack_volumes.server_id = '$Instance_ID'\nWHERE\n  $__timeFilter(ceph_volumes.created_at)\nORDER BY 1,2",
          "refId": "A",
          "select": [
            [
              {
                "params": [
                  "value"
                ],
                "type": "column"
              }
            ]
          ],
          "timeColumn": "time",
          "where": [
            {
              "name": "$__timeFilter",
              "params": [],
              "type": "macro"
            }
          ]
        }
      ],
      "timeFrom": null,
      "timeShift": null,
      "title": "Volume Total Utilization (%)",
      "type": "bargauge"
    },
    {
      "datasource": "${DS_PROMETHEUS}",
      "fieldConfig": {
        "defaults": {
          "color": {
            "mode": "thresholds"
          },
          "custom": {},
          "mappings": [],
          "thresholds": {
            "mode": "absolute",
            "steps": [
              {
                "color": "green",
                "value": null
              },
              {
                "color": "dark-yellow",
                "value": 0
              }
            ]
          }
        },
        "overrides": []
      },
      "gridPos": {
        "h": 3,
        "w": 4,
        "x": 4,
        "y": 4
      },
      "id": 9,
      "options": {
        "colorMode": "value",
        "graphMode": "none",
        "justifyMode": "auto",
        "orientation": "auto",
        "reduceOptions": {
          "calcs": [
            "lastNotNull"
          ],
          "fields": "",
          "values": false
        },
        "text": {},
        "textMode": "auto"
      },
      "pluginVersion": "7.3.7",
      "targets": [
        {
          "exemplar": true,
          "expr": "libvirt_domain_info_maximum_memory_bytes{domain=\"$domain\"}/1024/1024",
          "interval": "",
          "legendFormat": "",
          "refId": "A"
        }
      ],
      "title": "Memory (Mb)",
      "type": "stat"
    },
    {
      "datasource": "${DS_PROMETHEUS}",
      "description": "",
      "fieldConfig": {
        "defaults": {
          "color": {
            "mode": "thresholds"
          },
          "custom": {},
          "mappings": [],
          "thresholds": {
            "mode": "absolute",
            "steps": [
              {
                "color": "green",
                "value": null
              },
              {
                "color": "red",
                "value": 80
              }
            ]
          }
        },
        "overrides": []
      },
      "gridPos": {
        "h": 4,
        "w": 4,
        "x": 0,
        "y": 5
      },
      "id": 4,
      "options": {
        "colorMode": "value",
        "graphMode": "none",
        "justifyMode": "center",
        "orientation": "auto",
        "reduceOptions": {
          "calcs": [
            "last"
          ],
          "fields": "",
          "values": false
        },
        "text": {},
        "textMode": "name"
      },
      "pluginVersion": "7.3.7",
      "targets": [
        {
          "exemplar": true,
          "expr": "libvirt_domain_info_meta{project_name=\"$Project\",instance_name=\"$Instance_Name\"}",
          "format": "time_series",
          "instant": false,
          "interval": "",
          "legendFormat": "{{flavor}}",
          "refId": "A"
        }
      ],
      "timeFrom": null,
      "timeShift": null,
      "title": "Flavor",
      "type": "stat"
    },
    {
      "datasource": "${DS_PROMETHEUS}",
      "fieldConfig": {
        "defaults": {
          "custom": {
            "align": "center",
            "displayMode": "color-text",
            "filterable": false
          },
          "mappings": [],
          "thresholds": {
            "mode": "absolute",
            "steps": [
              {
                "color": "yellow",
                "value": null
              }
            ]
          }
        },
        "overrides": []
      },
      "gridPos": {
        "h": 2,
        "w": 4,
        "x": 8,
        "y": 5
      },
      "id": 35,
      "options": {
        "showHeader": false
      },
      "pluginVersion": "7.3.7",
      "targets": [
        {
          "expr": "libvirt_domain_info_meta{domain=\"$domain\"}",
          "format": "table",
          "instant": true,
          "interval": "",
          "legendFormat": "",
          "refId": "A"
        }
      ],
      "timeFrom": null,
      "timeShift": null,
      "title": "User",
      "transformations": [
        {
          "id": "organize",
          "options": {
            "excludeByName": {
              "Time": true,
              "Value": true,
              "__name__": true,
              "domain": true,
              "flavor": true,
              "instance": true,
              "instance_name": true,
              "job": true,
              "project_name": true,
              "project_uuid": true,
              "user_uuid": true,
              "uuid": true
            },
            "indexByName": {},
            "renameByName": {}
          }
        }
      ],
      "type": "table"
    },
    {
      "datasource": "${DS_PROMETHEUS}",
      "description": "",
      "fieldConfig": {
        "defaults": {
          "color": {
            "mode": "thresholds"
          },
          "custom": {},
          "mappings": [],
          "thresholds": {
            "mode": "absolute",
            "steps": [
              {
                "color": "orange",
                "value": null
              }
            ]
          }
        },
        "overrides": []
      },
      "gridPos": {
        "h": 2,
        "w": 4,
        "x": 12,
        "y": 5
      },
      "id": 26,
      "options": {
        "colorMode": "value",
        "graphMode": "none",
        "justifyMode": "auto",
        "orientation": "auto",
        "reduceOptions": {
          "calcs": [
            "lastNotNull"
          ],
          "fields": "",
          "values": false
        },
        "text": {},
        "textMode": "auto"
      },
      "pluginVersion": "7.3.7",
      "targets": [
        {
          "exemplar": true,
          "expr": "sum(libvirt_domain_block_meta{domain=\"$domain\"})",
          "interval": "",
          "legendFormat": "{{target_device}}",
          "refId": "A"
        }
      ],
      "title": "Number of Volumes",
      "type": "stat"
    },
    {
      "datasource": "${DS_PROMETHEUS}",
      "fieldConfig": {
        "defaults": {
          "color": {
            "mode": "thresholds"
          },
          "custom": {},
          "mappings": [],
          "thresholds": {
            "mode": "absolute",
            "steps": [
              {
                "color": "green",
                "value": null
              },
              {
                "color": "dark-yellow",
                "value": 0
              }
            ]
          }
        },
        "overrides": []
      },
      "gridPos": {
        "h": 2,
        "w": 4,
        "x": 4,
        "y": 7
      },
      "id": 18,
      "options": {
        "colorMode": "value",
        "graphMode": "none",
        "justifyMode": "auto",
        "orientation": "auto",
        "reduceOptions": {
          "calcs": [
            "lastNotNull"
          ],
          "fields": "",
          "values": false
        },
        "text": {},
        "textMode": "auto"
      },
      "pluginVersion": "7.3.7",
      "targets": [
        {
          "exemplar": true,
          "expr": "sum(libvirt_domain_interface_meta{domain=\"$domain\"})",
          "interval": "",
          "legendFormat": "",
          "refId": "A"
        }
      ],
      "title": "Network Interfaces",
      "type": "stat"
    },
    {
      "collapsed": false,
      "datasource": "${DS_PROMETHEUS}",
      "gridPos": {
        "h": 1,
        "w": 24,
        "x": 0,
        "y": 9
      },
      "id": 13,
      "panels": [],
      "title": "Utilization",
      "type": "row"
    },
    {
      "aliasColors": {},
      "bars": false,
      "dashLength": 10,
      "dashes": false,
      "datasource": "${DS_PROMETHEUS}",
      "description": "",
      "fieldConfig": {
        "defaults": {
          "custom": {},
          "unit": "percent"
        },
        "overrides": []
      },
      "fill": 7,
      "fillGradient": 10,
      "gridPos": {
        "h": 7,
        "w": 16,
        "x": 0,
        "y": 10
      },
      "hiddenSeries": false,
      "id": 11,
      "legend": {
        "alignAsTable": true,
        "avg": true,
        "current": true,
        "max": true,
        "min": true,
        "rightSide": false,
        "show": true,
        "total": false,
        "values": true
      },
      "lines": true,
      "linewidth": 2,
      "nullPointMode": "null",
      "options": {
        "alertThreshold": true
      },
      "percentage": false,
      "pluginVersion": "7.3.7",
      "pointradius": 2,
      "points": false,
      "renderer": "flot",
      "seriesOverrides": [],
      "spaceLength": 10,
      "stack": false,
      "steppedLine": false,
      "targets": [
        {
          "exemplar": true,
          "expr": "irate(libvirt_domain_info_cpu_time_seconds_total{domain=\"$domain\"}[2m])*100 / libvirt_domain_info_virtual_cpus{domain=\"$domain\"}",
          "interval": "",
          "legendFormat": "{{domain}}",
          "refId": "A"
        }
      ],
      "thresholds": [
        {
          "$$hashKey": "object:470",
          "colorMode": "critical",
          "fill": false,
          "line": true,
          "op": "gt",
          "value": 90,
          "yaxis": "left"
        },
        {
          "$$hashKey": "object:640",
          "colorMode": "warning",
          "fill": true,
          "line": true,
          "op": "gt",
          "value": 80,
          "yaxis": "left"
        }
      ],
      "timeFrom": null,
      "timeRegions": [],
      "timeShift": null,
      "title": "CPU Utilization",
      "tooltip": {
        "shared": true,
        "sort": 0,
        "value_type": "individual"
      },
      "type": "graph",
      "xaxis": {
        "buckets": null,
        "mode": "time",
        "name": null,
        "show": true,
        "values": []
      },
      "yaxes": [
        {
          "$$hashKey": "object:2575",
          "format": "percent",
          "label": null,
          "logBase": 1,
          "max": null,
          "min": null,
          "show": true
        },
        {
          "$$hashKey": "object:2576",
          "format": "short",
          "label": null,
          "logBase": 1,
          "max": null,
          "min": null,
          "show": true
        }
      ],
      "yaxis": {
        "align": false,
        "alignLevel": null
      }
    },
    {
      "aliasColors": {},
      "bars": true,
      "dashLength": 10,
      "dashes": false,
      "datasource": "${DS_PROMETHEUS}",
      "description": "",
      "fieldConfig": {
        "defaults": {
          "custom": {},
          "unit": "mbytes"
        },
        "overrides": []
      },
      "fill": 4,
      "fillGradient": 5,
      "gridPos": {
        "h": 7,
        "w": 7,
        "x": 16,
        "y": 10
      },
      "hiddenSeries": false,
      "id": 39,
      "legend": {
        "alignAsTable": true,
        "avg": true,
        "current": false,
        "max": true,
        "min": true,
        "rightSide": false,
        "show": true,
        "total": false,
        "values": true
      },
      "lines": false,
      "linewidth": 2,
      "nullPointMode": "null",
      "options": {
        "alertThreshold": true
      },
      "percentage": false,
      "pluginVersion": "7.3.7",
      "pointradius": 2,
      "points": false,
      "renderer": "flot",
      "seriesOverrides": [],
      "spaceLength": 10,
      "stack": false,
      "steppedLine": false,
      "targets": [
        {
          "exemplar": true,
          "expr": "libvirt_domain_memory_stats_available_bytes{domain=\"$domain\"}/1024/1024",
          "interval": "",
          "legendFormat": "Available Mbytes",
          "refId": "A"
        }
      ],
      "thresholds": [
        {
          "$$hashKey": "object:3173",
          "colorMode": "critical",
          "fill": true,
          "line": true,
          "op": "lt",
          "value": 1024,
          "yaxis": "right"
        },
        {
          "$$hashKey": "object:3192",
          "colorMode": "warning",
          "fill": true,
          "line": true,
          "op": "lt",
          "value": 2048,
          "yaxis": "right"
        },
        {
          "$$hashKey": "object:3198",
          "colorMode": "ok",
          "fill": true,
          "line": true,
          "op": "gt",
          "value": 2048,
          "yaxis": "right"
        }
      ],
      "timeFrom": null,
      "timeRegions": [],
      "timeShift": null,
      "title": "Memory Available Mbytes",
      "tooltip": {
        "shared": true,
        "sort": 0,
        "value_type": "individual"
      },
      "type": "graph",
      "xaxis": {
        "buckets": null,
        "mode": "time",
        "name": null,
        "show": true,
        "values": []
      },
      "yaxes": [
        {
          "$$hashKey": "object:989",
          "format": "mbytes",
          "label": null,
          "logBase": 1,
          "max": null,
          "min": null,
          "show": true
        },
        {
          "$$hashKey": "object:990",
          "format": "short",
          "label": null,
          "logBase": 1,
          "max": null,
          "min": null,
          "show": true
        }
      ],
      "yaxis": {
        "align": false,
        "alignLevel": null
      }
    },
    {
      "aliasColors": {},
      "bars": false,
      "dashLength": 10,
      "dashes": false,
      "datasource": "${DS_PROMETHEUS}",
      "description": "",
      "fieldConfig": {
        "defaults": {
          "custom": {},
          "unit": "percent"
        },
        "overrides": []
      },
      "fill": 4,
      "fillGradient": 5,
      "gridPos": {
        "h": 7,
        "w": 16,
        "x": 0,
        "y": 17
      },
      "hiddenSeries": false,
      "id": 16,
      "legend": {
        "alignAsTable": true,
        "avg": true,
        "current": true,
        "max": true,
        "min": true,
        "rightSide": false,
        "show": true,
        "total": false,
        "values": true
      },
      "lines": true,
      "linewidth": 2,
      "nullPointMode": "null",
      "options": {
        "alertThreshold": true
      },
      "percentage": false,
      "pluginVersion": "7.3.7",
      "pointradius": 2,
      "points": false,
      "renderer": "flot",
      "seriesOverrides": [],
      "spaceLength": 10,
      "stack": false,
      "steppedLine": false,
      "targets": [
        {
          "exemplar": true,
          "expr": "libvirt_domain_memory_stats_used_percent{domain=\"$domain\"}",
          "interval": "",
          "legendFormat": "{{domain}}",
          "refId": "A"
        }
      ],
      "thresholds": [
        {
          "$$hashKey": "object:470",
          "colorMode": "critical",
          "fill": false,
          "line": true,
          "op": "gt",
          "value": 90,
          "yaxis": "left"
        }
      ],
      "timeFrom": null,
      "timeRegions": [],
      "timeShift": null,
      "title": "Mem Utilization",
      "tooltip": {
        "shared": true,
        "sort": 0,
        "value_type": "individual"
      },
      "type": "graph",
      "xaxis": {
        "buckets": null,
        "mode": "time",
        "name": null,
        "show": true,
        "values": []
      },
      "yaxes": [
        {
          "$$hashKey": "object:989",
          "format": "percent",
          "label": null,
          "logBase": 1,
          "max": null,
          "min": null,
          "show": true
        },
        {
          "$$hashKey": "object:990",
          "format": "short",
          "label": null,
          "logBase": 1,
          "max": null,
          "min": null,
          "show": true
        }
      ],
      "yaxis": {
        "align": false,
        "alignLevel": null
      }
    },
    {
      "aliasColors": {},
      "bars": true,
      "dashLength": 10,
      "dashes": false,
      "datasource": "${DS_PROMETHEUS}",
      "description": "The amount of memory, that can be quickly reclaimed without additional I/O (in bytes).Typically these pages are used for caching files from disk.",
      "fieldConfig": {
        "defaults": {
          "custom": {},
          "unit": "deckbytes"
        },
        "overrides": []
      },
      "fill": 4,
      "fillGradient": 5,
      "gridPos": {
        "h": 6,
        "w": 7,
        "x": 16,
        "y": 17
      },
      "hiddenSeries": false,
      "id": 40,
      "legend": {
        "alignAsTable": true,
        "avg": true,
        "current": false,
        "max": true,
        "min": true,
        "rightSide": false,
        "show": true,
        "total": false,
        "values": true
      },
      "lines": false,
      "linewidth": 2,
      "nullPointMode": "null",
      "options": {
        "alertThreshold": true
      },
      "percentage": false,
      "pluginVersion": "7.3.7",
      "pointradius": 2,
      "points": false,
      "renderer": "flot",
      "seriesOverrides": [],
      "spaceLength": 10,
      "stack": false,
      "steppedLine": false,
      "targets": [
        {
          "exemplar": true,
          "expr": "libvirt_domain_memory_stats_disk_cache_bytes{domain=\"$domain\"}/1024",
          "interval": "",
          "legendFormat": "Memory Cache Kbytes",
          "refId": "A"
        }
      ],
      "thresholds": [],
      "timeFrom": null,
      "timeRegions": [],
      "timeShift": null,
      "title": "Memory Disk Caches",
      "tooltip": {
        "shared": true,
        "sort": 0,
        "value_type": "individual"
      },
      "type": "graph",
      "xaxis": {
        "buckets": null,
        "mode": "time",
        "name": null,
        "show": true,
        "values": []
      },
      "yaxes": [
        {
          "$$hashKey": "object:989",
          "format": "deckbytes",
          "label": null,
          "logBase": 1,
          "max": null,
          "min": null,
          "show": true
        },
        {
          "$$hashKey": "object:990",
          "format": "short",
          "label": null,
          "logBase": 1,
          "max": null,
          "min": null,
          "show": true
        }
      ],
      "yaxis": {
        "align": false,
        "alignLevel": null
      }
    },
    {
      "collapsed": false,
      "datasource": "${DS_PROMETHEUS}",
      "gridPos": {
        "h": 1,
        "w": 24,
        "x": 0,
        "y": 24
      },
      "id": 23,
      "panels": [],
      "title": "Volume Details",
      "type": "row"
    },
    {
      "aliasColors": {},
      "bars": false,
      "dashLength": 10,
      "dashes": false,
      "datasource": "${DS_POSTGRESQL}",
      "description": "Used size in GB",
      "fieldConfig": {
        "defaults": {
          "custom": {}
        },
        "overrides": []
      },
      "fill": 2,
      "fillGradient": 2,
      "gridPos": {
        "h": 8,
        "w": 12,
        "x": 0,
        "y": 25
      },
      "hiddenSeries": false,
      "id": 43,
      "legend": {
        "avg": false,
        "current": false,
        "max": false,
        "min": false,
        "show": true,
        "total": false,
        "values": false
      },
      "lines": true,
      "linewidth": 3,
      "nullPointMode": "null",
      "options": {
        "alertThreshold": true
      },
      "percentage": false,
      "pluginVersion": "7.3.7",
      "pointradius": 3,
      "points": true,
      "renderer": "flot",
      "seriesOverrides": [],
      "spaceLength": 10,
      "stack": false,
      "steppedLine": false,
      "targets": [
        {
          "format": "time_series",
          "group": [],
          "metricColumn": "ceph_volumes.usedsize",
          "rawQuery": true,
          "rawSql": "SELECT\n  ceph_volumes.created_at AS \"time\",\n  ceph_volumes.usedsize,\n  openstack_volumes.device AS metric\nFROM ceph_volumes\nINNER JOIN openstack_volumes\nON ceph_volumes.id = openstack_volumes.id\n  AND openstack_volumes.status = 'in-use'\n  AND openstack_volumes.server_id = '$Instance_ID'\nWHERE\n  $__timeFilter(ceph_volumes.created_at)\nORDER BY 1,2",
          "refId": "A",
          "select": [
            [
              {
                "params": [
                  "ceph_volumes.usedsize"
                ],
                "type": "column"
              }
            ]
          ],
          "table": "ceph_volumes",
          "timeColumn": "ceph_volumes.created_at",
          "timeColumnType": "timestamptz",
          "where": [
            {
              "name": "$__timeFilter",
              "params": [],
              "type": "macro"
            },
            {
              "name": "",
              "params": [
                "openstack_volumes.server_id",
                "=",
                "$Instance_ID"
              ],
              "type": "expression"
            }
          ]
        }
      ],
      "thresholds": [
        {
          "$$hashKey": "object:526",
          "colorMode": "critical",
          "fill": true,
          "line": true,
          "op": "gt",
          "yaxis": "left"
        }
      ],
      "timeFrom": null,
      "timeRegions": [],
      "timeShift": null,
      "title": "Disk Volumes Used Size in GB",
      "tooltip": {
        "shared": true,
        "sort": 0,
        "value_type": "individual"
      },
      "type": "graph",
      "xaxis": {
        "buckets": null,
        "mode": "time",
        "name": null,
        "show": true,
        "values": []
      },
      "yaxes": [
        {
          "format": "short",
          "label": null,
          "logBase": 1,
          "max": null,
          "min": null,
          "show": true
        },
        {
          "format": "short",
          "label": null,
          "logBase": 1,
          "max": null,
          "min": null,
          "show": true
        }
      ],
      "yaxis": {
        "align": false,
        "alignLevel": null
      }
    },
    {
      "datasource": "${DS_PROMETHEUS}",
      "description": "",
      "fieldConfig": {
        "defaults": {
          "custom": {},
          "mappings": [],
          "thresholds": {
            "mode": "absolute",
            "steps": [
              {
                "color": "purple",
                "value": null
              }
            ]
          }
        },
        "overrides": []
      },
      "gridPos": {
        "h": 8,
        "w": 7,
        "x": 12,
        "y": 25
      },
      "id": 21,
      "options": {
        "displayMode": "lcd",
        "orientation": "horizontal",
        "reduceOptions": {
          "calcs": [
            "mean"
          ],
          "fields": "",
          "values": false
        },
        "showUnfilled": true
      },
      "pluginVersion": "7.3.7",
      "targets": [
        {
          "expr": "libvirt_domain_block_stats_physicalsize_bytes{domain=\"$domain\"}/1024/1024/1024",
          "interval": "",
          "legendFormat": "{{target_device}}",
          "refId": "A"
        }
      ],
      "timeFrom": null,
      "timeShift": null,
      "title": "Disk Total Size (GB)",
      "type": "bargauge"
    },
    {
      "aliasColors": {},
      "bars": false,
      "dashLength": 10,
      "dashes": false,
      "datasource": "${DS_PROMETHEUS}",
      "description": "",
      "fieldConfig": {
        "defaults": {
          "custom": {}
        },
        "overrides": []
      },
      "fill": 3,
      "fillGradient": 6,
      "gridPos": {
        "h": 8,
        "w": 12,
        "x": 0,
        "y": 33
      },
      "hiddenSeries": false,
      "id": 25,
      "legend": {
        "avg": false,
        "current": false,
        "max": false,
        "min": false,
        "show": true,
        "total": false,
        "values": false
      },
      "lines": true,
      "linewidth": 2,
      "nullPointMode": "null",
      "options": {
        "alertThreshold": true
      },
      "percentage": false,
      "pluginVersion": "7.3.7",
      "pointradius": 2,
      "points": false,
      "renderer": "flot",
      "seriesOverrides": [],
      "spaceLength": 10,
      "stack": false,
      "steppedLine": false,
      "targets": [
        {
          "expr": "irate(libvirt_domain_block_stats_read_bytes_total{domain=\"$domain\"}[5m])",
          "interval": "",
          "legendFormat": "{{target_device}} - Successfully read bytes",
          "refId": "A"
        },
        {
          "expr": "irate(libvirt_domain_block_stats_write_bytes_total{domain=\"$domain\"}[5m])",
          "interval": "",
          "legendFormat": "{{target_device}} - Successfully write bytes",
          "refId": "B"
        }
      ],
      "thresholds": [],
      "timeFrom": null,
      "timeRegions": [],
      "timeShift": null,
      "title": "I/O Usage Read/Write",
      "tooltip": {
        "shared": true,
        "sort": 0,
        "value_type": "individual"
      },
      "type": "graph",
      "xaxis": {
        "buckets": null,
        "mode": "time",
        "name": null,
        "show": true,
        "values": []
      },
      "yaxes": [
        {
          "format": "short",
          "label": null,
          "logBase": 1,
          "max": null,
          "min": null,
          "show": true
        },
        {
          "format": "short",
          "label": null,
          "logBase": 1,
          "max": null,
          "min": null,
          "show": true
        }
      ],
      "yaxis": {
        "align": false,
        "alignLevel": null
      }
    },
    {
      "aliasColors": {},
      "bars": false,
      "dashLength": 10,
      "dashes": false,
      "datasource": "${DS_PROMETHEUS}",
      "description": "Number of Read and write requests from/to block device",
      "fieldConfig": {
        "defaults": {
          "custom": {}
        },
        "overrides": []
      },
      "fill": 3,
      "fillGradient": 6,
      "gridPos": {
        "h": 8,
        "w": 12,
        "x": 12,
        "y": 33
      },
      "hiddenSeries": false,
      "id": 27,
      "legend": {
        "alignAsTable": true,
        "avg": true,
        "current": false,
        "max": true,
        "min": true,
        "show": true,
        "total": false,
        "values": true
      },
      "lines": true,
      "linewidth": 2,
      "nullPointMode": "null",
      "options": {
        "alertThreshold": true
      },
      "percentage": false,
      "pluginVersion": "7.3.7",
      "pointradius": 2,
      "points": false,
      "renderer": "flot",
      "seriesOverrides": [],
      "spaceLength": 10,
      "stack": false,
      "steppedLine": false,
      "targets": [
        {
          "expr": "irate(libvirt_domain_block_stats_read_requests_total{domain=\"$domain\"}[5m])",
          "interval": "",
          "intervalFactor": 4,
          "legendFormat": "{{target_device}} - Reads Request Rate",
          "refId": "A"
        },
        {
          "expr": "irate(libvirt_domain_block_stats_write_requests_total{domain=\"$domain\"}[5m])",
          "interval": "",
          "intervalFactor": 2,
          "legendFormat": "{{target_device}} - Write Request Rate",
          "refId": "B"
        }
      ],
      "thresholds": [],
      "timeFrom": null,
      "timeRegions": [],
      "timeShift": null,
      "title": "Disk R/W Requests IOPS",
      "tooltip": {
        "shared": true,
        "sort": 0,
        "value_type": "individual"
      },
      "type": "graph",
      "xaxis": {
        "buckets": null,
        "mode": "time",
        "name": null,
        "show": true,
        "values": []
      },
      "yaxes": [
        {
          "$$hashKey": "object:1008",
          "decimals": null,
          "format": "Request Rate",
          "label": "Request Rate",
          "logBase": 1,
          "max": null,
          "min": null,
          "show": true
        },
        {
          "$$hashKey": "object:1009",
          "format": "short",
          "label": null,
          "logBase": 1,
          "max": null,
          "min": null,
          "show": true
        }
      ],
      "yaxis": {
        "align": false,
        "alignLevel": null
      }
    },
    {
      "aliasColors": {},
      "bars": true,
      "dashLength": 10,
      "dashes": false,
      "datasource": "${DS_PROMETHEUS}",
      "description": "Total time in seconds spent on cache flushing to a block device",
      "fieldConfig": {
        "defaults": {
          "custom": {},
          "unit": "percent"
        },
        "overrides": []
      },
      "fill": 4,
      "fillGradient": 5,
      "gridPos": {
        "h": 8,
        "w": 12,
        "x": 0,
        "y": 41
      },
      "hiddenSeries": false,
      "id": 41,
      "legend": {
        "alignAsTable": true,
        "avg": true,
        "current": false,
        "max": false,
        "min": false,
        "rightSide": false,
        "show": true,
        "total": false,
        "values": true
      },
      "lines": false,
      "linewidth": 2,
      "nullPointMode": "null",
      "options": {
        "alertThreshold": true
      },
      "percentage": false,
      "pluginVersion": "7.3.7",
      "pointradius": 2,
      "points": false,
      "renderer": "flot",
      "seriesOverrides": [],
      "spaceLength": 10,
      "stack": false,
      "steppedLine": false,
      "targets": [
        {
          "exemplar": true,
          "expr": "irate(libvirt_domain_block_stats_flush_time_seconds_total{domain=\"$domain\"}[10m])",
          "interval": "",
          "legendFormat": "{{target_device}}",
          "refId": "A"
        }
      ],
      "thresholds": [],
      "timeFrom": null,
      "timeRegions": [],
      "timeShift": null,
      "title": "cache flush to block device",
      "tooltip": {
        "shared": true,
        "sort": 0,
        "value_type": "individual"
      },
      "type": "graph",
      "xaxis": {
        "buckets": null,
        "mode": "time",
        "name": null,
        "show": true,
        "values": []
      },
      "yaxes": [
        {
          "$$hashKey": "object:989",
          "format": "percent",
          "label": null,
          "logBase": 1,
          "max": null,
          "min": null,
          "show": true
        },
        {
          "$$hashKey": "object:990",
          "format": "short",
          "label": null,
          "logBase": 1,
          "max": null,
          "min": null,
          "show": true
        }
      ],
      "yaxis": {
        "align": false,
        "alignLevel": null
      }
    },
    {
      "collapsed": false,
      "datasource": "${DS_PROMETHEUS}",
      "gridPos": {
        "h": 1,
        "w": 24,
        "x": 0,
        "y": 49
      },
      "id": 29,
      "panels": [],
      "title": "Interface Details",
      "type": "row"
    },
    {
      "aliasColors": {},
      "bars": false,
      "dashLength": 10,
      "dashes": false,
      "datasource": "${DS_PROMETHEUS}",
      "description": "",
      "fieldConfig": {
        "defaults": {
          "custom": {}
        },
        "overrides": []
      },
      "fill": 1,
      "fillGradient": 0,
      "gridPos": {
        "h": 8,
        "w": 12,
        "x": 0,
        "y": 50
      },
      "hiddenSeries": false,
      "id": 31,
      "legend": {
        "alignAsTable": true,
        "avg": true,
        "current": true,
        "max": true,
        "min": true,
        "show": true,
        "total": false,
        "values": true
      },
      "lines": true,
      "linewidth": 1,
      "nullPointMode": "null",
      "options": {
        "alertThreshold": true
      },
      "percentage": false,
      "pluginVersion": "7.3.7",
      "pointradius": 2,
      "points": false,
      "renderer": "flot",
      "seriesOverrides": [
        {
          "$$hashKey": "object:1682",
          "alias": "/.*Trans.*/",
          "transform": "negative-Y"
        }
      ],
      "spaceLength": 10,
      "stack": false,
      "steppedLine": false,
      "targets": [
        {
          "expr": "irate(libvirt_domain_interface_stats_receive_packets_total{domain=\"$domain\"}[5m])",
          "interval": "",
          "intervalFactor": 2,
          "legendFormat": "{{target_device}} - Receive",
          "refId": "A"
        },
        {
          "expr": "irate(libvirt_domain_interface_stats_transmit_packets_total{domain=\"$domain\"}[5m])",
          "interval": "",
          "intervalFactor": 2,
          "legendFormat": "{{target_device}} - Transmit",
          "refId": "B"
        }
      ],
      "thresholds": [],
      "timeFrom": null,
      "timeRegions": [],
      "timeShift": null,
      "title": "Network Traffic by Packets",
      "tooltip": {
        "shared": true,
        "sort": 0,
        "value_type": "individual"
      },
      "type": "graph",
      "xaxis": {
        "buckets": null,
        "mode": "time",
        "name": null,
        "show": true,
        "values": []
      },
      "yaxes": [
        {
          "$$hashKey": "object:1654",
          "decimals": null,
          "format": "pps",
          "label": "packets out (-) / in (+)",
          "logBase": 1,
          "max": null,
          "min": null,
          "show": true
        },
        {
          "$$hashKey": "object:1655",
          "format": "short",
          "label": null,
          "logBase": 1,
          "max": null,
          "min": null,
          "show": true
        }
      ],
      "yaxis": {
        "align": false,
        "alignLevel": null
      }
    },
    {
      "aliasColors": {},
      "bars": false,
      "dashLength": 10,
      "dashes": false,
      "datasource": "${DS_PROMETHEUS}",
      "description": "",
      "fieldConfig": {
        "defaults": {
          "custom": {}
        },
        "overrides": []
      },
      "fill": 1,
      "fillGradient": 0,
      "gridPos": {
        "h": 8,
        "w": 12,
        "x": 12,
        "y": 50
      },
      "hiddenSeries": false,
      "id": 38,
      "legend": {
        "alignAsTable": true,
        "avg": true,
        "current": true,
        "max": true,
        "min": true,
        "show": true,
        "total": false,
        "values": true
      },
      "lines": true,
      "linewidth": 1,
      "nullPointMode": "null",
      "options": {
        "alertThreshold": true
      },
      "percentage": false,
      "pluginVersion": "7.3.7",
      "pointradius": 2,
      "points": false,
      "renderer": "flot",
      "seriesOverrides": [
        {
          "$$hashKey": "object:1682",
          "alias": "/.*Trans.*/",
          "transform": "negative-Y"
        }
      ],
      "spaceLength": 10,
      "stack": false,
      "steppedLine": false,
      "targets": [
        {
          "expr": "irate(libvirt_domain_interface_stats_receive_bytes_total{domain=\"$domain\"}[5m])/1024",
          "interval": "",
          "intervalFactor": 2,
          "legendFormat": "{{target_device}} - Kbytes Recieved",
          "refId": "A"
        },
        {
          "expr": "irate(libvirt_domain_interface_stats_transmit_bytes_total{domain=\"$domain\"}[5m])/1024",
          "interval": "",
          "intervalFactor": 2,
          "legendFormat": "{{target_device}} - Kbytes Transmitted",
          "refId": "B"
        }
      ],
      "thresholds": [],
      "timeFrom": null,
      "timeRegions": [],
      "timeShift": null,
      "title": "Network Traffic by Bytes",
      "tooltip": {
        "shared": true,
        "sort": 0,
        "value_type": "individual"
      },
      "type": "graph",
      "xaxis": {
        "buckets": null,
        "mode": "time",
        "name": null,
        "show": true,
        "values": []
      },
      "yaxes": [
        {
          "$$hashKey": "object:1654",
          "decimals": null,
          "format": "kbytes",
          "label": "Kbytes out (-) / in (+)",
          "logBase": 1,
          "max": null,
          "min": null,
          "show": true
        },
        {
          "$$hashKey": "object:1655",
          "format": "short",
          "label": null,
          "logBase": 1,
          "max": null,
          "min": null,
          "show": true
        }
      ],
      "yaxis": {
        "align": false,
        "alignLevel": null
      }
    },
    {
      "aliasColors": {},
      "bars": true,
      "dashLength": 10,
      "dashes": false,
      "datasource": "${DS_PROMETHEUS}",
      "description": "",
      "fieldConfig": {
        "defaults": {
          "custom": {}
        },
        "overrides": []
      },
      "fill": 1,
      "fillGradient": 0,
      "gridPos": {
        "h": 8,
        "w": 12,
        "x": 0,
        "y": 58
      },
      "hiddenSeries": false,
      "id": 36,
      "legend": {
        "alignAsTable": true,
        "avg": true,
        "current": true,
        "max": true,
        "min": true,
        "show": true,
        "total": false,
        "values": true
      },
      "lines": false,
      "linewidth": 1,
      "nullPointMode": "null",
      "options": {
        "alertThreshold": true
      },
      "percentage": false,
      "pluginVersion": "7.3.7",
      "pointradius": 2,
      "points": false,
      "renderer": "flot",
      "seriesOverrides": [
        {
          "$$hashKey": "object:1682",
          "alias": "/.*Trans.*/",
          "transform": "negative-Y"
        }
      ],
      "spaceLength": 10,
      "stack": false,
      "steppedLine": false,
      "targets": [
        {
          "expr": "irate(libvirt_domain_interface_stats_receive_errors_total{domain=\"$domain\"}[5m])",
          "interval": "",
          "intervalFactor": 2,
          "legendFormat": "{{target_device}} - Receive errors",
          "refId": "A"
        },
        {
          "expr": "irate(libvirt_domain_interface_stats_transmit_errors_total{domain=\"$domain\"}[5m])",
          "interval": "",
          "intervalFactor": 2,
          "legendFormat": "{{target_device}} - Transmit errors",
          "refId": "B"
        }
      ],
      "thresholds": [],
      "timeFrom": null,
      "timeRegions": [],
      "timeShift": null,
      "title": "Network Traffic Errors",
      "tooltip": {
        "shared": true,
        "sort": 0,
        "value_type": "individual"
      },
      "type": "graph",
      "xaxis": {
        "buckets": null,
        "mode": "time",
        "name": null,
        "show": true,
        "values": []
      },
      "yaxes": [
        {
          "$$hashKey": "object:1654",
          "decimals": null,
          "format": "pps",
          "label": "packets out (-) / in (+)",
          "logBase": 1,
          "max": null,
          "min": null,
          "show": true
        },
        {
          "$$hashKey": "object:1655",
          "format": "short",
          "label": null,
          "logBase": 1,
          "max": null,
          "min": null,
          "show": true
        }
      ],
      "yaxis": {
        "align": false,
        "alignLevel": null
      }
    },
    {
      "aliasColors": {},
      "bars": true,
      "dashLength": 10,
      "dashes": false,
      "datasource": "${DS_PROMETHEUS}",
      "description": "",
      "fieldConfig": {
        "defaults": {
          "custom": {}
        },
        "overrides": []
      },
      "fill": 1,
      "fillGradient": 0,
      "gridPos": {
        "h": 8,
        "w": 12,
        "x": 12,
        "y": 58
      },
      "hiddenSeries": false,
      "id": 37,
      "legend": {
        "alignAsTable": true,
        "avg": true,
        "current": true,
        "max": true,
        "min": true,
        "show": true,
        "total": false,
        "values": true
      },
      "lines": false,
      "linewidth": 1,
      "nullPointMode": "null",
      "options": {
        "alertThreshold": true
      },
      "percentage": false,
      "pluginVersion": "7.3.7",
      "pointradius": 2,
      "points": false,
      "renderer": "flot",
      "seriesOverrides": [
        {
          "$$hashKey": "object:1682",
          "alias": "/.*Trans.*/",
          "transform": "negative-Y"
        }
      ],
      "spaceLength": 10,
      "stack": false,
      "steppedLine": false,
      "targets": [
        {
          "expr": "irate(libvirt_domain_interface_stats_receive_drops_total{domain=\"$domain\"}[5m])",
          "interval": "",
          "intervalFactor": 2,
          "legendFormat": "{{target_device}} - Receive drops",
          "refId": "A"
        },
        {
          "expr": "irate(libvirt_domain_interface_stats_transmit_drops_total{domain=\"$domain\"}[5m])",
          "interval": "",
          "intervalFactor": 2,
          "legendFormat": "{{target_device}} - Transmit drops",
          "refId": "B"
        }
      ],
      "thresholds": [],
      "timeFrom": null,
      "timeRegions": [],
      "timeShift": null,
      "title": "Network Traffic Drops",
      "tooltip": {
        "shared": true,
        "sort": 0,
        "value_type": "individual"
      },
      "type": "graph",
      "xaxis": {
        "buckets": null,
        "mode": "time",
        "name": null,
        "show": true,
        "values": []
      },
      "yaxes": [
        {
          "$$hashKey": "object:1654",
          "decimals": null,
          "format": "pps",
          "label": "packets out (-) / in (+)",
          "logBase": 1,
          "max": null,
          "min": null,
          "show": true
        },
        {
          "$$hashKey": "object:1655",
          "format": "short",
          "label": null,
          "logBase": 1,
          "max": null,
          "min": null,
          "show": true
        }
      ],
      "yaxis": {
        "align": false,
        "alignLevel": null
      }
    },
    {
      "datasource": "${DS_PROMETHEUS}",
      "description": "",
      "fieldConfig": {
        "defaults": {
          "custom": {
            "align": "left",
            "filterable": false
          },
          "mappings": [],
          "thresholds": {
            "mode": "absolute",
            "steps": [
              {
                "color": "green",
                "value": null
              },
              {
                "color": "red",
                "value": 80
              }
            ]
          }
        },
        "overrides": [
          {
            "matcher": {
              "id": "byName",
              "options": "Time"
            },
            "properties": []
          }
        ]
      },
      "gridPos": {
        "h": 8,
        "w": 12,
        "x": 0,
        "y": 66
      },
      "id": 33,
      "options": {
        "showHeader": true,
        "sortBy": []
      },
      "pluginVersion": "7.3.7",
      "targets": [
        {
          "expr": "libvirt_domain_interface_meta{domain=\"$domain\"}",
          "format": "table",
          "instant": true,
          "interval": "",
          "legendFormat": "{{source_bridge}}",
          "refId": "A"
        }
      ],
      "timeFrom": null,
      "timeShift": null,
      "title": "",
      "transformations": [
        {
          "id": "organize",
          "options": {
            "excludeByName": {
              "Time": true,
              "Value": true,
              "__name__": true,
              "domain": true,
              "instance": true,
              "job": true
            },
            "indexByName": {},
            "renameByName": {}
          }
        }
      ],
      "transparent": true,
      "type": "table"
    }
  ],
  "refresh": false,
  "schemaVersion": 26,
  "style": "dark",
  "tags": [],
  "templating": {
    "list": [
      {
        "allValue": null,
        "current": {},
        "datasource": "${DS_PROMETHEUS}",
        "definition": "label_values(project_name)",
        "description": "Select Project Name",
        "error": null,
        "hide": 0,
        "includeAll": false,
        "label": "Project",
        "multi": false,
        "name": "Project",
        "options": [],
        "query": "label_values(project_name)",
        "refresh": 1,
        "regex": "",
        "skipUrlSync": false,
        "sort": 0,
        "tagValuesQuery": "",
        "tags": [],
        "tagsQuery": "",
        "type": "query",
        "useTags": false
      },
      {
        "allValue": null,
        "current": {},
        "datasource": "${DS_PROMETHEUS}",
        "definition": "label_values(libvirt_domain_info_meta{project_name=\"$Project\"}, instance_name)",
        "description": null,
        "error": null,
        "hide": 0,
        "includeAll": false,
        "label": "Instance",
        "multi": false,
        "name": "Instance_Name",
        "options": [],
        "query": "label_values(libvirt_domain_info_meta{project_name=\"$Project\"}, instance_name)",
        "refresh": 1,
        "regex": "",
        "skipUrlSync": false,
        "sort": 0,
        "tagValuesQuery": "",
        "tags": [],
        "tagsQuery": "",
        "type": "query",
        "useTags": false
      },
      {
        "allValue": null,
        "current": {},
        "datasource": "${DS_PROMETHEUS}",
        "definition": "label_values(libvirt_domain_info_meta{project_name=\"$Project\",instance_name=\"$Instance_Name\"}, domain)",
        "description": null,
        "error": null,
        "hide": 1,
        "includeAll": false,
        "label": null,
        "multi": false,
        "name": "domain",
        "options": [],
        "query": "label_values(libvirt_domain_info_meta{project_name=\"$Project\",instance_name=\"$Instance_Name\"}, domain)",
        "refresh": 1,
        "regex": "",
        "skipUrlSync": false,
        "sort": 0,
        "tagValuesQuery": "",
        "tags": [],
        "tagsQuery": "",
        "type": "query",
        "useTags": false
      },
      {
        "allValue": null,
        "current": {},
        "datasource": "${DS_PROMETHEUS}",
        "definition": "label_values(libvirt_domain_info_meta{project_name=\"$Project\",instance_name=\"$Instance_Name\"},uuid)",
        "error": null,
        "hide": 2,
        "includeAll": false,
        "label": "Instance_ID",
        "multi": false,
        "name": "Instance_ID",
        "options": [],
        "query": "label_values(libvirt_domain_info_meta{project_name=\"$Project\",instance_name=\"$Instance_Name\"},uuid)",
        "refresh": 1,
        "regex": "",
        "skipUrlSync": false,
        "sort": 0,
        "tagValuesQuery": "",
        "tags": [],
        "tagsQuery": "",
        "type": "query",
        "useTags": false
      }
    ]
  },
  "time": {
    "from": "now-6h",
    "to": "now"
  },
  "timepicker": {},
  "timezone": "",
  "title": "libvirt_exporter Instances",
  "uid": "V5NLZKXGk",
  "version": 37,
  "description": "libvirt_exporter for displaying tenant Instance metric details\r\n\r\n\r\n\r\nhttps://github.com/AlexZzz/libvirt-exporter.git"
}